setup.py
pytest_disable/__init__.py
pytest_disable/__version__.py
pytest_disable.egg-info/PKG-INFO
pytest_disable.egg-info/SOURCES.txt
pytest_disable.egg-info/dependency_links.txt
pytest_disable.egg-info/entry_points.txt
pytest_disable.egg-info/pbr.json
pytest_disable.egg-info/requires.txt
pytest_disable.egg-info/top_level.txt